KM2/RAM.sv
module RAM 
#(parameter DATA_WIDTH=8, parameter ADDR_WIDTH=8)
(
	input logic [(DATA_WIDTH-1):0] data,
	input  logic [(ADDR_WIDTH-1):0] addr,
	input logic we, clk,
	output logic [(DATA_WIDTH-1):0] q
);

	logic [DATA_WIDTH-1:0] ram[2**ADDR_WIDTH-1:0];

	logic [ADDR_WIDTH-1:0] addr_reg;

    initial
    begin
        $readmemb("rom128x8.txt", ram, 2**ADDR_WIDTH-1, 0);
    end

	always @ (posedge clk)
	begin
		// Write
		if (we)
			ram[addr] <= data;

		addr_reg <= addr;
	end
    
	assign q = ram[addr_reg];

endmodule

KM2/RAM_tb.sv
`include "RAM.sv"
`timescale 1 ps/ 1 ps
module ROM_tb;

logic [7:0] j;
logic clk, we;
logic [7:0] q;
logic [7:0] d;
int t = 52; // Здесь менять сид

RAM #(.DATA_WIDTH(8), .ADDR_WIDTH(8)) DUT (.addr(j), .clk(clk), .q(q), .we(we), .data(d));
initial begin
    clk = 0;
    we = 0;
end 
always #1 clk = !clk;
initial j = 0;
initial begin
    for (int i = 0; i < 5; i++) begin
        j=$urandom(t) % 256;
        #5;
        d=$urandom(t) % 256;
        we = 1;
        #2 we = 0;
        #3;
    end

end
initial #100 $finish;
initial begin
    $dumpfile("RAM_tb.vcd");
    $dumpvars(0, ROM_tb);
end

endmodule

KM2/RAM_tb.vcd
$date
	Thu Oct 03 16:27:12 2024
$end
$version
	Icarus Verilog
$end
$timescale
	1ps
$end
$scope module ROM_tb $end
$var wire 8 ! q [7:0] $end
$var reg 1 " clk $end
$var reg 8 # d [7:0] $end
$var reg 8 $ j [7:0] $end
$var reg 1 % we $end
$var integer 32 & t [31:0] $end
$scope module DUT $end
$var wire 8 ' addr [7:0] $end
$var wire 1 " clk $end
$var wire 8 ( data [7:0] $end
$var wire 8 ) q [7:0] $end
$var wire 1 % we $end
$var parameter 32 * ADDR_WIDTH $end
$var parameter 32 + DATA_WIDTH $end
$var reg 8 , addr_reg [7:0] $end
$upscope $end
$scope begin $ivl_for_loop0 $end
$var integer 32 - i [31:0] $end
$upscope $end
$upscope $end
$enddefinitions $end
$comment Show the parameter values. $end
$dumpall
b1000 +
b1000 *
$end
#0
$dumpvars
b0 -
bx ,
bx )
bx (
b0 '
b1101101100110110100101 &
0%
b0 $
bx #
0"
bx !
$end
#1
b1001000 !
b1001000 )
b0 ,
1"
#2
0"
#3
1"
#4
0"
#5
b10000011 !
b10000011 )
1"
1%
b10000011 #
b10000011 (
b11000001111110010000111000100010 &
#6
0"
#7
1"
0%
#8
0"
#9
1"
#10
0"
b10000 $
b10000 '
b1000010010100000101100111011 &
b1 -
#11
b1111100 !
b1111100 )
b10000 ,
1"
#12
0"
#13
1"
#14
0"
#15
b11100010 !
b11100010 )
1"
1%
b11100010 #
b11100010 (
b1110001000101111111110101000000 &
#16
0"
#17
1"
0%
#18
0"
#19
1"
#20
0"
b10001010 $
b10001010 '
b11000101010100100000110001000001 &
b10 -
#21
b11111111 !
b11111111 )
b10001010 ,
1"
#22
0"
#23
1"
#24
0"
#25
b1110011 !
b1110011 )
1"
1%
b1110011 #
b1110011 (
b111001100101000001110100001110 &
#26
0"
#27
1"
0%
#28
0"
#29
1"
#30
0"
b1111100 $
b1111100 '
b10111110001000101111101000110111 &
b11 -
#31
b10101 !
b10101 )
b1111100 ,
1"
#32
0"
#33
1"
#34
0"
#35
b101 !
b101 )
1"
1%
b101 #
b101 (
b10111011100010100100001100 &
#36
0"
#37
1"
0%
#38
0"
#39
1"
#40
0"
b110011 $
b110011 '
b10011001110110000111101010011101 &
b100 -
#41
b11100011 !
b11100011 )
b110011 ,
1"
#42
0"
#43
1"
#44
0"
#45
b1010110 !
b1010110 )
1"
1%
b1010110 #
b1010110 (
b10101011001100010010100010111010 &
#46
0"
#47
1"
0%
#48
0"
#49
1"
#50
0"
b101 -
